{
  "last_updated": "2026-03-15T11:20:22.194037",
  "event_count": 20,
  "events": [
    {
      "category": "Boxing",
      "date": "21/03/2026",
      "end_date": "21/03/2026",
      "end_time": "06:00:00",
      "eventLogo": "https://static.wikia.nocookie.net/wweuniverse/images/f/f6/Wwelogo.png/revision/latest?cb=20101124080717",
      "eventName": "Friday Night SmackDown",
      "id": 20,
      "links": [
        {
          "api": "333962e3e1383529867a9a0e28a5e5d1:5d3fcbed53749ee622ed0e64f31c1cbf",
          "link": "https://gg.poocloud.in/wrestling/index.m3u8|referer=https://ppv.to/&origin=https://ppv.to",
          "name": "SP ",
          "scheme": 0,
          "tokenApi": ""
        },
        {
          "api": "dadpremium343,newkso.ru,aHR0cHM6Ly9qeG94a3BsYXkueHl6",
          "link": "https://red9.lumenlyra.space/playlist/36017/load-playlist?|Referer=https://gooz.aapmains.net",
          "name": "SP - 2",
          "scheme": 0,
          "tokenApi": ""
        }
      ],
      "teamAFlag": "https://assets.primesport.com/prod/images/Smackdown%202025%20Updated%20Logo.png",
      "teamAName": "SmackDown",
      "teamBFlag": "https://assets.primesport.com/prod/images/Smackdown%202025%20Updated%20Logo.png",
      "teamBName": "SmackDown",
      "time": "01:00:00",
      "visible": true
    },
    {
      "category": "Motorsports",
      "date": "15/03/2026",
      "end_date": "",
      "end_time": "",
      "eventLogo": "https://access-control-center-prod.freevision.live/ss/category/36.png",
      "eventName": "Formula1 - Bahrain Test",
      "id": 22,
      "links": [
        {
          "api": "",
          "link": "https://stream.huraweb.com/embed_view.php?id=75ea48132cd87cee",
          "name": "Sky Sports - IOS",
          "scheme": 0,
          "tokenApi": ""
        },
        {
          "api": "2fbdaa3bea0d0323ae011b318d1db716:8726ef7eaf5b9dce15fb6aa9f80bd53f",
          "link": "https://ottb.live.cf.ww.aiv-cdn.net/iad-nitro/live/clients/dash/enc/oboxe53wyo/out/v1/f7892a9d706d419a846d738fa22ea33e/cenc.mpd",
          "name": "Fox Sports - AQ",
          "scheme": 0,
          "tokenApi": ""
        },
        {
          "api": "",
          "link": "https://smarthard.click/hls/91LHlS9qZPK5/index.m3u8",
          "name": "Sky F1 SD",
          "scheme": 0,
          "tokenApi": ""
        },
        {
          "api": "",
          "link": "https://stream.huraweb.com/embed_view.php?id=b3fa79aa26476de9",
          "name": "Sky F1 HD - IOS",
          "scheme": 0,
          "tokenApi": ""
        },
        {
          "api": "",
          "link": "https://stream.huraweb.com/embed_view.php?id=a119bff323d5cdbb",
          "name": "Sky Sports HD - IOS",
          "scheme": 0,
          "tokenApi": ""
        },
        {
          "api": "",
          "link": "https://smarthard.click/hls/07HL6dzqKCAr/index.m3u8",
          "name": "Sky F1 DE",
          "scheme": 0,
          "tokenApi": ""
        },
        {
          "api": "7e9239c1982d984a002df3ed049d0756:1b8a17598129a3618535c8fb05f103fe",
          "link": "https://ottb.live.cf.ww.aiv-cdn.net/lhr-nitro/live/clients/dash/enc/fdb3pubmek/out/v1/aefca6420f944a9482e117f315de535f/cenc.mpd",
          "name": "Fancode AQ",
          "scheme": 0,
          "tokenApi": ""
        }
      ],
      "teamAFlag": "https://access-control-center-prod.freevision.live/ss/category/36.png",
      "teamAName": "Formula 1",
      "teamBFlag": "https://access-control-center-prod.freevision.live/ss/category/36.png",
      "teamBName": "Formula 1",
      "time": "07:00:00",
      "visible": true
    },
    {
      "category": "Cricket",
      "date": "15/03/2026",
      "end_date": "15/03/2026",
      "end_time": "16:30:00",
      "eventLogo": "http://api.sofascore.com/api/v1/unique-tournament/11190/image/dark",
      "eventName": "One Day International",
      "id": 23,
      "links": [
        {
          "api": "b01896dfc4f780aa0e61765af00128b1:0390e22ecb9b6ef93ddf8f7cd3b38461",
          "link": "https://otte.cache.aiv-cdn.net/bom-nitro/live/clients/dash/enc/8ntichuuto/out/v1/f7b575d5d9a949f9a4e164f635ebb9c7/cenc.mpd",
          "name": "WILLOW - AQ",
          "scheme": 0,
          "tokenApi": ""
        },
        {
          "api": "",
          "link": "http://195.178.110.27/hls/FUUUQQQ.m3u8|Referer=http://www.fawanews.sc/",
          "name": "WILLOW - LQ",
          "scheme": 0,
          "tokenApi": ""
        },
        {
          "api": "",
          "link": "https://premierleagpl23.akamaized.net/hls/live/2107108/tapmad479832/master.m3u8",
          "name": "TAPMAD - AQ",
          "scheme": 0,
          "tokenApi": ""
        },
        {
          "api": "",
          "link": "https://live.incableinternet.com/v/kooker_ptvsportshd/kooker_ptvsportshd.mpd",
          "name": "PTV SPORTS",
          "scheme": 0,
          "tokenApi": ""
        },
        {
          "api": "",
          "link": "http://198.195.239.50:8095/Tsports/index.m3u8",
          "name": "TSports SD",
          "scheme": 0,
          "tokenApi": ""
        }
      ],
      "teamAFlag": "https://img.sofascore.com/api/v1/team/187744/image",
      "teamAName": "Bangladesh",
      "teamBFlag": "https://img.sofascore.com/api/v1/team/187754/image",
      "teamBName": "Pakistan",
      "time": "08:15:00",
      "visible": true
    },
    {
      "category": "Cricket",
      "date": "15/03/2026",
      "end_date": "15/03/2026",
      "end_time": "10:25:00",
      "eventLogo": "http://api.sofascore.com/api/v1/unique-tournament/11191/image/dark",
      "eventName": "T20 International",
      "id": 41,
      "links": [
        {
          "api": "192b1115da041585c77200128549efa1:634e10efe4abbb14be400a3ccbac0258",
          "link": "https://otte.cache.aiv-cdn.net/bom-nitro/live/clients/dash/enc/pnu10tp36z/out/v1/912e9db56d75403b8a9ac0a719110f36/cenc.mpd",
          "name": "TNT SPORTS - AQ",
          "scheme": 0,
          "tokenApi": ""
        }
      ],
      "teamAFlag": "https://img.sofascore.com/api/v1/team/187755/image",
      "teamAName": "New Zealand",
      "teamBFlag": "https://img.sofascore.com/api/v1/team/187747/image",
      "teamBName": "South Africa",
      "time": "06:15:00",
      "visible": true
    },
    {
      "category": "Football",
      "date": "15/03/2026",
      "end_date": "15/03/2026",
      "end_time": "13:50:00",
      "eventLogo": "http://api.sofascore.com/api/v1/unique-tournament/23/image/dark",
      "eventName": "Serie A",
      "id": 42,
      "links": [
        {
          "link": "https://no.link",
          "name": "Link 1"
        }
      ],
      "teamAFlag": "https://img.sofascore.com/api/v1/team/2701/image",
      "teamAName": "Hellas Verona",
      "teamBFlag": "https://img.sofascore.com/api/v1/team/2713/image",
      "teamBName": "Genoa",
      "time": "11:30:00",
      "visible": true
    },
    {
      "category": "Football",
      "date": "15/03/2026",
      "end_date": "15/03/2026",
      "end_time": "22:20:00",
      "eventLogo": "http://api.sofascore.com/api/v1/unique-tournament/8/image/dark",
      "eventName": "LaLiga",
      "id": 43,
      "links": [
        {
          "link": "https://no.link",
          "name": "Link 1"
        }
      ],
      "teamAFlag": "https://img.sofascore.com/api/v1/team/2824/image",
      "teamAName": "Real Sociedad",
      "teamBFlag": "https://img.sofascore.com/api/v1/team/2820/image",
      "teamBName": "Osasuna",
      "time": "20:00:00",
      "visible": true
    },
    {
      "category": "Football",
      "date": "15/03/2026",
      "end_date": "15/03/2026",
      "end_time": "19:20:00",
      "eventLogo": "http://api.sofascore.com/api/v1/unique-tournament/23/image/dark",
      "eventName": "Serie A",
      "id": 44,
      "links": [
        {
          "link": "https://no.link",
          "name": "Link 1"
        }
      ],
      "teamAFlag": "https://img.sofascore.com/api/v1/team/2704/image",
      "teamAName": "Como",
      "teamBFlag": "https://img.sofascore.com/api/v1/team/2702/image",
      "teamBName": "Roma",
      "time": "17:00:00",
      "visible": true
    },
    {
      "category": "Football",
      "date": "15/03/2026",
      "end_date": "15/03/2026",
      "end_time": "16:20:00",
      "eventLogo": "http://api.sofascore.com/api/v1/unique-tournament/17/image/dark",
      "eventName": "Premier League",
      "id": 45,
      "links": [
        {
          "link": "https://no.link",
          "name": "Link 1"
        }
      ],
      "teamAFlag": "https://img.sofascore.com/api/v1/team/7/image",
      "teamAName": "Crystal Palace",
      "teamBFlag": "https://img.sofascore.com/api/v1/team/34/image",
      "teamBName": "Leeds United",
      "time": "14:00:00",
      "visible": true
    },
    {
      "category": "Football",
      "date": "15/03/2026",
      "end_date": "15/03/2026",
      "end_time": "16:20:00",
      "eventLogo": "http://api.sofascore.com/api/v1/unique-tournament/17/image/dark",
      "eventName": "Premier League",
      "id": 46,
      "links": [
        {
          "link": "https://no.link",
          "name": "Link 1"
        }
      ],
      "teamAFlag": "https://img.sofascore.com/api/v1/team/14/image",
      "teamAName": "Nottingham Forest",
      "teamBFlag": "https://img.sofascore.com/api/v1/team/43/image",
      "teamBName": "Fulham",
      "time": "14:00:00",
      "visible": true
    },
    {
      "category": "Football",
      "date": "15/03/2026",
      "end_date": "15/03/2026",
      "end_time": "22:05:00",
      "eventLogo": "http://api.sofascore.com/api/v1/unique-tournament/23/image/dark",
      "eventName": "Serie A",
      "id": 47,
      "links": [
        {
          "link": "https://no.link",
          "name": "Link 1"
        }
      ],
      "teamAFlag": "https://img.sofascore.com/api/v1/team/2699/image",
      "teamAName": "Lazio",
      "teamBFlag": "https://img.sofascore.com/api/v1/team/2692/image",
      "teamBName": "Milan",
      "time": "19:45:00",
      "visible": true
    },
    {
      "category": "Football",
      "date": "15/03/2026",
      "end_date": "15/03/2026",
      "end_time": "15:20:00",
      "eventLogo": "http://api.sofascore.com/api/v1/unique-tournament/8/image/dark",
      "eventName": "LaLiga",
      "id": 48,
      "links": [
        {
          "link": "https://no.link",
          "name": "Link 1"
        }
      ],
      "teamAFlag": "https://img.sofascore.com/api/v1/team/2826/image",
      "teamAName": "Mallorca",
      "teamBFlag": "https://img.sofascore.com/api/v1/team/2814/image",
      "teamBName": "Espanyol",
      "time": "13:00:00",
      "visible": true
    },
    {
      "category": "Football",
      "date": "15/03/2026",
      "end_date": "15/03/2026",
      "end_time": "16:20:00",
      "eventLogo": "http://api.sofascore.com/api/v1/unique-tournament/17/image/dark",
      "eventName": "Premier League",
      "id": 49,
      "links": [
        {
          "link": "https://no.link",
          "name": "Link 1"
        }
      ],
      "teamAFlag": "https://img.sofascore.com/api/v1/team/35/image",
      "teamAName": "Manchester United",
      "teamBFlag": "https://img.sofascore.com/api/v1/team/40/image",
      "teamBName": "Aston Villa",
      "time": "14:00:00",
      "visible": true
    },
    {
      "category": "Football",
      "date": "15/03/2026",
      "end_date": "15/03/2026",
      "end_time": "16:20:00",
      "eventLogo": "http://api.sofascore.com/api/v1/unique-tournament/23/image/dark",
      "eventName": "Serie A",
      "id": 50,
      "links": [
        {
          "link": "https://no.link",
          "name": "Link 1"
        }
      ],
      "teamAFlag": "https://img.sofascore.com/api/v1/team/2793/image",
      "teamAName": "Sassuolo",
      "teamBFlag": "https://img.sofascore.com/api/v1/team/2685/image",
      "teamBName": "Bologna",
      "time": "14:00:00",
      "visible": true
    },
    {
      "category": "Football",
      "date": "15/03/2026",
      "end_date": "15/03/2026",
      "end_time": "18:50:00",
      "eventLogo": "http://api.sofascore.com/api/v1/unique-tournament/17/image/dark",
      "eventName": "Premier League",
      "id": 51,
      "links": [
        {
          "link": "https://no.link",
          "name": "Link 1"
        }
      ],
      "teamAFlag": "https://img.sofascore.com/api/v1/team/44/image",
      "teamAName": "Liverpool",
      "teamBFlag": "https://img.sofascore.com/api/v1/team/33/image",
      "teamBName": "Tottenham Hotspur",
      "time": "16:30:00",
      "visible": true
    },
    {
      "category": "Football",
      "date": "15/03/2026",
      "end_date": "15/03/2026",
      "end_time": "19:50:00",
      "eventLogo": "http://api.sofascore.com/api/v1/unique-tournament/8/image/dark",
      "eventName": "LaLiga",
      "id": 52,
      "links": [
        {
          "link": "https://no.link",
          "name": "Link 1"
        }
      ],
      "teamAFlag": "https://img.sofascore.com/api/v1/team/2816/image",
      "teamAName": "Real Betis",
      "teamBFlag": "https://img.sofascore.com/api/v1/team/2821/image",
      "teamBName": "Celta Vigo",
      "time": "17:30:00",
      "visible": true
    },
    {
      "category": "Football",
      "date": "15/03/2026",
      "end_date": "15/03/2026",
      "end_time": "18:50:00",
      "eventLogo": "http://api.sofascore.com/api/v1/unique-tournament/35/image/dark",
      "eventName": "Bundesliga",
      "id": 53,
      "links": [
        {
          "link": "https://no.link",
          "name": "Link 1"
        }
      ],
      "teamAFlag": "https://img.sofascore.com/api/v1/team/2538/image",
      "teamAName": "SC Freiburg",
      "teamBFlag": "https://img.sofascore.com/api/v1/team/2547/image",
      "teamBName": "1. FC Union Berlin",
      "time": "16:30:00",
      "visible": true
    },
    {
      "category": "Football",
      "date": "15/03/2026",
      "end_date": "15/03/2026",
      "end_time": "16:20:00",
      "eventLogo": "http://api.sofascore.com/api/v1/unique-tournament/23/image/dark",
      "eventName": "Serie A",
      "id": 54,
      "links": [
        {
          "link": "https://no.link",
          "name": "Link 1"
        }
      ],
      "teamAFlag": "https://img.sofascore.com/api/v1/team/2737/image",
      "teamAName": "Pisa",
      "teamBFlag": "https://img.sofascore.com/api/v1/team/2719/image",
      "teamBName": "Cagliari",
      "time": "14:00:00",
      "visible": true
    },
    {
      "category": "Football",
      "date": "15/03/2026",
      "end_date": "15/03/2026",
      "end_time": "16:50:00",
      "eventLogo": "http://api.sofascore.com/api/v1/unique-tournament/35/image/dark",
      "eventName": "Bundesliga",
      "id": 55,
      "links": [
        {
          "link": "https://no.link",
          "name": "Link 1"
        }
      ],
      "teamAFlag": "https://img.sofascore.com/api/v1/team/2534/image",
      "teamAName": "SV Werder Bremen",
      "teamBFlag": "https://img.sofascore.com/api/v1/team/2556/image",
      "teamBName": "1. FSV Mainz 05",
      "time": "14:30:00",
      "visible": true
    },
    {
      "category": "Football",
      "date": "15/03/2026",
      "end_date": "15/03/2026",
      "end_time": "17:35:00",
      "eventLogo": "http://api.sofascore.com/api/v1/unique-tournament/8/image/dark",
      "eventName": "LaLiga",
      "id": 56,
      "links": [
        {
          "link": "https://no.link",
          "name": "Link 1"
        }
      ],
      "teamAFlag": "https://img.sofascore.com/api/v1/team/2817/image",
      "teamAName": "Barcelona",
      "teamBFlag": "https://img.sofascore.com/api/v1/team/2833/image",
      "teamBName": "Sevilla",
      "time": "15:15:00",
      "visible": true
    },
    {
      "category": "Football",
      "date": "15/03/2026",
      "end_date": "15/03/2026",
      "end_time": "20:50:00",
      "eventLogo": "http://api.sofascore.com/api/v1/unique-tournament/35/image/dark",
      "eventName": "Bundesliga",
      "id": 57,
      "links": [
        {
          "link": "https://no.link",
          "name": "Link 1"
        }
      ],
      "teamAFlag": "https://img.sofascore.com/api/v1/team/2677/image",
      "teamAName": "VfB Stuttgart",
      "teamBFlag": "https://img.sofascore.com/api/v1/team/36360/image",
      "teamBName": "RB Leipzig",
      "time": "18:30:00",
      "visible": true
    }
  ]
}