{
  "last_updated": "2026-03-18T17:40:25.348669",
  "event_count": 10,
  "events": [
    {
      "category": "Boxing",
      "date": "21/03/2026",
      "end_date": "21/03/2026",
      "end_time": "06:00:00",
      "eventLogo": "https://static.wikia.nocookie.net/wweuniverse/images/f/f6/Wwelogo.png/revision/latest?cb=20101124080717",
      "eventName": "Friday Night SmackDown",
      "id": 20,
      "links": [
        {
          "api": "333962e3e1383529867a9a0e28a5e5d1:5d3fcbed53749ee622ed0e64f31c1cbf",
          "link": "https://gg.poocloud.in/wrestling/index.m3u8|referer=https://ppv.to/&origin=https://ppv.to",
          "name": "SP ",
          "scheme": 0,
          "tokenApi": ""
        },
        {
          "api": "dadpremium343,newkso.ru,aHR0cHM6Ly9qeG94a3BsYXkueHl6",
          "link": "https://red9.lumenlyra.space/playlist/36017/load-playlist?|Referer=https://gooz.aapmains.net",
          "name": "SP - 2",
          "scheme": 0,
          "tokenApi": ""
        }
      ],
      "teamAFlag": "https://assets.primesport.com/prod/images/Smackdown%202025%20Updated%20Logo.png",
      "teamAName": "SmackDown",
      "teamBFlag": "https://assets.primesport.com/prod/images/Smackdown%202025%20Updated%20Logo.png",
      "teamBName": "SmackDown",
      "time": "01:00:00",
      "visible": true
    },
    {
      "category": "Motorsports",
      "date": "27/03/2026",
      "end_date": "",
      "end_time": "",
      "eventLogo": "https://access-control-center-prod.freevision.live/ss/category/36.png",
      "eventName": "Formula1 - Bahrain Test",
      "id": 22,
      "links": [
        {
          "api": "",
          "link": "https://stream.huraweb.com/embed_view.php?id=75ea48132cd87cee",
          "name": "Sky Sports - IOS",
          "scheme": 0,
          "tokenApi": ""
        },
        {
          "api": "2fbdaa3bea0d0323ae011b318d1db716:8726ef7eaf5b9dce15fb6aa9f80bd53f",
          "link": "https://ottb.live.cf.ww.aiv-cdn.net/iad-nitro/live/clients/dash/enc/oboxe53wyo/out/v1/f7892a9d706d419a846d738fa22ea33e/cenc.mpd",
          "name": "Fox Sports - AQ",
          "scheme": 0,
          "tokenApi": ""
        },
        {
          "api": "",
          "link": "https://smarthard.click/hls/91LHlS9qZPK5/index.m3u8",
          "name": "Sky F1 SD",
          "scheme": 0,
          "tokenApi": ""
        },
        {
          "api": "",
          "link": "https://stream.huraweb.com/embed_view.php?id=b3fa79aa26476de9",
          "name": "Sky F1 HD - IOS",
          "scheme": 0,
          "tokenApi": ""
        },
        {
          "api": "",
          "link": "https://stream.huraweb.com/embed_view.php?id=a119bff323d5cdbb",
          "name": "Sky Sports HD - IOS",
          "scheme": 0,
          "tokenApi": ""
        },
        {
          "api": "",
          "link": "https://smarthard.click/hls/07HL6dzqKCAr/index.m3u8",
          "name": "Sky F1 DE",
          "scheme": 0,
          "tokenApi": ""
        },
        {
          "api": "7e9239c1982d984a002df3ed049d0756:1b8a17598129a3618535c8fb05f103fe",
          "link": "https://ottb.live.cf.ww.aiv-cdn.net/lhr-nitro/live/clients/dash/enc/fdb3pubmek/out/v1/aefca6420f944a9482e117f315de535f/cenc.mpd",
          "name": "Fancode AQ",
          "scheme": 0,
          "tokenApi": ""
        }
      ],
      "teamAFlag": "https://access-control-center-prod.freevision.live/ss/category/36.png",
      "teamAName": "Formula 1",
      "teamBFlag": "https://access-control-center-prod.freevision.live/ss/category/36.png",
      "teamBName": "Formula 1",
      "time": "02:30:00",
      "visible": true
    },
    {
      "category": "Football",
      "date": "18/03/2026",
      "end_date": "18/03/2026",
      "end_time": "22:20:00",
      "eventLogo": "http://api.sofascore.com/api/v1/unique-tournament/7/image/dark",
      "eventName": "UEFA Champions League",
      "id": 23,
      "links": [
        {
          "link": "https://no.link",
          "name": "Link 1"
        }
      ],
      "teamAFlag": "https://img.sofascore.com/api/v1/team/2672/image",
      "teamAName": "FC Bayern München",
      "teamBFlag": "https://img.sofascore.com/api/v1/team/2686/image",
      "teamBName": "Atalanta",
      "time": "20:00:00",
      "visible": true
    },
    {
      "category": "Football",
      "date": "18/03/2026",
      "end_date": "18/03/2026",
      "end_time": "22:20:00",
      "eventLogo": "http://api.sofascore.com/api/v1/unique-tournament/7/image/dark",
      "eventName": "UEFA Champions League",
      "id": 24,
      "links": [
        {
          "link": "https://no.link",
          "name": "Link 1"
        }
      ],
      "teamAFlag": "https://img.sofascore.com/api/v1/team/33/image",
      "teamAName": "Tottenham Hotspur",
      "teamBFlag": "https://img.sofascore.com/api/v1/team/2836/image",
      "teamBName": "Atlético Madrid",
      "time": "20:00:00",
      "visible": true
    },
    {
      "category": "Football",
      "date": "18/03/2026",
      "end_date": "18/03/2026",
      "end_time": "20:05:00",
      "eventLogo": "http://api.sofascore.com/api/v1/unique-tournament/7/image/dark",
      "eventName": "UEFA Champions League",
      "id": 25,
      "links": [
        {
          "api": "f288380ca4cef9ad3f27a92a08e9bb8b:9f18d26291d9230833501f7f822f6875",
          "link": "https://otte.cache.aiv-cdn.net/bom-nitro/live/clients/dash/enc/fb6jy4pxts/out/v1/f8fa17f087564f51aa4d5c700be43ec4/cenc.mpd",
          "name": "TNT SPORTS - AQ",
          "scheme": 0,
          "tokenApi": ""
        },
        {
          "api": "a772d39f9db4e13a7ddb20c834146c08:a21842563cb7098af614b82e7d5d4636",
          "link": "https://otte.cache.aiv-cdn.net/gru-nitro/live/clients/dash/enc/kpooidebh6/out/v1/0a5fbcc3fc124cf9b996201087a58b2f/cenc.mpd",
          "name": "TNT BRASIL - AQ",
          "scheme": 0,
          "tokenApi": ""
        },
        {
          "api": "cb705d43ec369891b851a078cabfac5c:fdfefad94eac611692a9e790f266ae4d",
          "link": "https://cdn3.skygo.mn/live/disk1/SPSPrime/STRM-CH2-1/SPSPrime.mpd",
          "name": "PSN SPORTS - AQ",
          "scheme": 0,
          "tokenApi": ""
        },
        {
          "api": "",
          "link": "https://wnt-geting-002.transmisjana.digital/52f4d0221c11473f80b11de1d952f8b4.m3u8|origin=https://hmembeds.one&user-agent=Mozilla/5.0 (Windows NT 10.0; Win64; x64) AppleWebKit/537.36 (KHTML, like Gecko) Chrome/146.0.0.0 Safari/537.36",
          "name": "TNT SPORTS FHD",
          "scheme": 0,
          "tokenApi": ""
        },
        {
          "api": "",
          "link": "https://kipperltvs.s3.us-east-1.amazonaws.com/main.m3u8",
          "name": "HD SERVER ",
          "scheme": 0,
          "tokenApi": ""
        },
        {
          "api": "",
          "link": "https://bbb.exoadash.com/TVD4077/index.mpd",
          "name": "COSMOTE SPORTS",
          "scheme": 0,
          "tokenApi": ""
        }
      ],
      "teamAFlag": "https://img.sofascore.com/api/v1/team/2817/image",
      "teamAName": "Barcelona",
      "teamBFlag": "https://img.sofascore.com/api/v1/team/39/image",
      "teamBName": "Newcastle United",
      "time": "17:45:00",
      "visible": true
    },
    {
      "category": "Football",
      "date": "18/03/2026",
      "end_date": "18/03/2026",
      "end_time": "17:50:00",
      "eventLogo": "http://api.sofascore.com/api/v1/unique-tournament/679/image/dark",
      "eventName": "UEFA Europa League",
      "id": 26,
      "links": [
        {
          "api": "294b5761cefc22d0c6312939e13d8278:52148f1042d238849f0a7813f1da8a7b",
          "link": "https://otte.cache.aiv-cdn.net/bom-nitro/live/clients/dash/enc/cllekigzzn/out/v1/bd3b0c314fff4bb1ab4693358f3cd2d3/cenc.mpd",
          "name": "TNT SPORTS - AQ",
          "scheme": 0,
          "tokenApi": ""
        },
        {
          "api": "3cfa8625f650406ebf6a4d1ea737f572:0534e747c70b364aa7210e1bf3191df0",
          "link": "https://mag03.tvx.prd.tv.odido.nl/wh7f454c46tw266117884_-1972819316/PLTV/86/224/3221241560/3221241560.mpd?accountinfo=~~V2.0~OhA1DF4svOZppKxb-t-Ngw144cce44121c63284a33d5453493e5c8~1_Fmlu5PevHMYnEi9Z_HX2goKAd0VHSuxZMoIcAXcawYvG1meqGp2eQ2Ibhjvh7e59e7f6df3d57f23a32024ad67f0f19dc:UTC,",
          "name": "ZIGGO SPORTS",
          "scheme": 0,
          "tokenApi": ""
        }
      ],
      "teamAFlag": "https://img.sofascore.com/api/v1/team/2999/image",
      "teamAName": "Sporting Braga",
      "teamBFlag": "https://img.sofascore.com/api/v1/team/1925/image",
      "teamBName": "Ferencváros TC",
      "time": "15:30:00",
      "visible": true
    },
    {
      "category": "Football",
      "date": "18/03/2026",
      "end_date": "18/03/2026",
      "end_time": "22:20:00",
      "eventLogo": "http://api.sofascore.com/api/v1/unique-tournament/7/image/dark",
      "eventName": "UEFA Champions League",
      "id": 27,
      "links": [
        {
          "link": "https://no.link",
          "name": "Link 1"
        }
      ],
      "teamAFlag": "https://img.sofascore.com/api/v1/team/44/image",
      "teamAName": "Liverpool",
      "teamBFlag": "https://img.sofascore.com/api/v1/team/3061/image",
      "teamBName": "Galatasaray",
      "time": "20:00:00",
      "visible": true
    },
    {
      "category": "Football",
      "date": "18/03/2026",
      "end_date": "18/03/2026",
      "end_time": "21:20:00",
      "eventLogo": "http://api.sofascore.com/api/v1/unique-tournament/2058/image/dark",
      "eventName": "King's Cup",
      "id": 28,
      "links": [
        {
          "link": "https://no.link",
          "name": "Link 1"
        }
      ],
      "teamAFlag": "https://img.sofascore.com/api/v1/team/269199/image",
      "teamAName": "Al-Kholood",
      "teamBFlag": "https://img.sofascore.com/api/v1/team/34315/image",
      "teamBName": "Al-Ittihad",
      "time": "19:00:00",
      "visible": true
    },
    {
      "category": "Football",
      "date": "18/03/2026",
      "end_date": "18/03/2026",
      "end_time": "21:20:00",
      "eventLogo": "http://api.sofascore.com/api/v1/unique-tournament/2058/image/dark",
      "eventName": "King's Cup",
      "id": 29,
      "links": [
        {
          "link": "https://no.link",
          "name": "Link 1"
        }
      ],
      "teamAFlag": "https://img.sofascore.com/api/v1/team/34469/image",
      "teamAName": "Al-Ahli",
      "teamBFlag": "https://img.sofascore.com/api/v1/team/21895/image",
      "teamBName": "Al-Hilal",
      "time": "19:00:00",
      "visible": true
    },
    {
      "category": "Football",
      "date": "18/03/2026",
      "end_date": "18/03/2026",
      "end_time": "22:05:00",
      "eventLogo": "http://api.sofascore.com/api/v1/unique-tournament/18/image/dark",
      "eventName": "Championship",
      "id": 30,
      "links": [
        {
          "link": "https://no.link",
          "name": "Link 1"
        }
      ],
      "teamAFlag": "https://img.sofascore.com/api/v1/team/45/image",
      "teamAName": "Southampton",
      "teamBFlag": "https://img.sofascore.com/api/v1/team/263/image",
      "teamBName": "Norwich City",
      "time": "19:45:00",
      "visible": true
    }
  ]
}